hurocon/__init__.py
hurocon/__main__.py
hurocon/cli/__init__.py
hurocon/cli/auth.py
hurocon/cli/cli_base.py
hurocon/cli/config.py
hurocon/cli/device.py
hurocon/cli/lte.py
hurocon/cli/net.py
hurocon/cli/sms.py
hurocon/core/connection.py
hurocon/core/const.py
hurocon/core/io.py
hurocon/core/local_cfg.py
hurocon/implementation/__init__.py
hurocon/implementation/iauth.py
hurocon/implementation/iconfig.py
hurocon/implementation/idevice.py
hurocon/implementation/inet.py
hurocon/implementation/isms.py
hurocon/meta.py
hurocon-0.6.0.dist-info/entry_points.txt
hurocon-0.6.0.dist-info/LICENSE
hurocon-0.6.0.dist-info/WHEEL
hurocon-0.6.0.dist-info/METADATA
hurocon-0.6.0.dist-info/RECORD
