Metadata-Version: 2.1
Name: hurocon
Version: 0.6.0
Summary: Command line interface tool for interacting with Huawei LTE routers
Home-page: https://github.com/maximilionus/hurocon.git
License: MIT
Keywords: cli,huawei,router,control
Author: maximilionus
Author-email: maximilionuss@gmail.com
Requires-Python: >=3.7,<4.0
Classifier: Development Status :: 3 - Alpha
Classifier: Environment :: Console
Classifier: Intended Audience :: System Administrators
Classifier: Intended Audience :: Telecommunications Industry
Classifier: License :: OSI Approved :: MIT License
Classifier: Natural Language :: English
Classifier: Operating System :: OS Independent
Classifier: Programming Language :: Python :: 3
Classifier: Programming Language :: Python :: 3 :: Only
Classifier: Programming Language :: Python :: 3.10
Classifier: Programming Language :: Python :: 3.7
Classifier: Programming Language :: Python :: 3.8
Classifier: Programming Language :: Python :: 3.9
Requires-Dist: click (>=8.1.2,<9.0.0)
Requires-Dist: click-didyoumean (>=0.3.0,<0.4.0)
Requires-Dist: huawei-lte-api (>=1.6.0,<2.0.0)
Requires-Dist: jsonschema (>=4.7.2,<5.0.0)
Requires-Dist: pwinput (<=1.0.2)
Requires-Dist: serialix (>=2.4.1,<3.0.0)
Project-URL: Documentation, https://github.com/maximilionus/hurocon/blob/master/README.md
Project-URL: Repository, https://github.com/maximilionus/hurocon.git
